EastMoney/__init__.py
EastMoney-1.0.0.dist-info/LICENSE
EastMoney-1.0.0.dist-info/METADATA
EastMoney-1.0.0.dist-info/WHEEL
EastMoney-1.0.0.dist-info/top_level.txt
EastMoney-1.0.0.dist-info/RECORD
