Metadata-Version: 2.1
Name: EastMoney
Version: 1.0.0
Summary: Retrieve A-share information from EastMoney for Python
Home-page: https://github.com/HurinHu/EastMoney
Author: Hurin Hu
Author-email: hurin@live.ca
License: UNKNOWN
Platform: UNKNOWN
Classifier: Programming Language :: Python :: 3
Classifier: License :: OSI Approved :: MIT License
Classifier: Operating System :: OS Independent
